{"article_id": "9421364", "title": "澀谷事變？男赴日本東京十字路口縱火 路人驚慌畫面曝光", "date": "2026-04-03 21:36", "source": "聯合報", "author": "茅毅", "section": "即時報導", "cover_image": {"src": "https://pgw.udn.com.tw/gw/photo.php?u=https://uc.udn.com.tw/photo/t3/2026/04/03/34825595.jpg&M=1&x=0&y=0&sw=0&sh=0&sl=W&fw=800&exp=3600&w=930", "alt": "日本東京都澀谷區的知名十字路口「澀谷十字路口」3日晚間發生縱火案。圖／截自X@koto_chan影片畫面", "caption": "日本東京都澀谷區的知名十字路口「澀谷十字路口」3日晚間發生縱火案。圖／截自X@koto_chan影片畫面"}, "body": [{"type": "text", "content": "日本東京都澀谷區的知名十字路口「澀谷十字路口」3日晚間發生縱火案。"}, {"type": "text", "content": "根據日媒報導，1名男子於3日晚間9時（台灣時間當晚8時）多，突在該路口中央潑灑寶特瓶內的液體，並以準備好的打火機引燃，引發路人恐慌。"}, {"type": "text", "content": "據稱該路口為全球最繁忙的行人十字路口，綠燈時單次通行人數達3000人。"}, {"type": "text", "content": "twitter loading..."}, {"type": "text", "content": "twitter loading..."}, {"type": "text", "content": "twitter loading..."}]}