{"article_id": "9472783", "title": "川普在白宮會晤企業高層 CNN：討論持續封鎖伊朗數月措施", "date": "2026-04-29 22:35", "source": "聯合報", "author": "高詣軒", "section": "即時報導", "cover_image": {"src": "https://pgw.udn.com.tw/gw/photo.php?u=https://uc.udn.com.tw/photo/t3/2026/04/29/34902433.jpg&M=1&x=0&y=0&sw=0&sh=0&sl=W&fw=800&exp=3600&w=930", "alt": "美國總統川普28日在白宮，出席招待英王夫婦來訪的國宴。美聯社", "caption": "美國總統川普28日在白宮，出席招待英王夫婦來訪的國宴。美聯社"}, "body": [{"type": "text", "content": "美國有線電視新聞網（CNN）29日報導，美國總統川普和幾位高階幕僚28日在白宮會晤多位企業高層，討論若需要將封鎖伊朗港口行動持續幾個月，可採取的措施，以及如何控制這對美國消費者的影響。"}, {"type": "text", "content": "幾位白宮官員說，上述談話主題廣泛，涵蓋伊朗戰爭期間的油價壓力，以及委內瑞拉石油出口等問題。"}, {"type": "text", "content": "一位官員透露，美國財政部長貝森特主持該次會議，副總統范斯、白宮幕僚長威爾斯、中東特使威科夫、川普女婿庫許納也都出席。"}, {"type": "text", "content": "與會企業高層則包括雪佛龍執行長沃斯；此外，大宗商品交易巨擘托克集團、獨立石油貿易商維多集團、大宗商品貿易商摩科瑞的高層也出席。"}, {"type": "text", "content": "白宮官員說，川普經常會見能源業高層，聽取其對國內外能源市場的意見，這次討論國內生產、委內瑞拉局勢、石油期貨、天然氣、航運等議題。"}]}