{"article_id": "9481430", "title": "戰火重創能源命脈 傳卡達LNG不可抗力效期延長到6月中", "date": "2026-05-04 20:54", "source": "經濟日報", "author": "任中原", "section": "綜合外電", "cover_image": {"src": "https://pgw.udn.com.tw/gw/photo.php?u=https://uc.udn.com.tw/photo/t3/2026/05/04/34915629.jpg&M=1&s=Y&x=0&y=0&sw=1280&sh=853&sl=W&fw=800&exp=3600&w=930", "alt": "圖為台灣位於觀塘的LNG接收站。法新社", "caption": "圖為台灣位於觀塘的LNG接收站。法新社"}, "body": [{"type": "text", "content": "知情人士透露，卡達國家能源公司（QatarEnergy）已將液化天然氣（LNG）供應所遭遇的「不可抗力」效期延長到6月中旬，因為荷莫茲海峽幾乎完全封閉，使LNG無法運出。"}, {"type": "text", "content": "彭博引述知情人士報導，卡達能源公司的客戶已收到通知，但公司方面並未對此事做出立即回應。"}, {"type": "text", "content": "自從中東開戰以來，卡達能源公司已定期向客戶告知「不可抗力」依然有效。位於卡達、全球最大LNG廠區Ras Laffan於3月遭到伊朗飛彈攻擊，受損嚴重。"}]}