{"article_id": "9489166", "title": "英國7名旅客下船後2人自主隔離 世衛表示漢他病毒不是新冠亦非流感", "date": "2026-05-07 22:50", "source": "聯合報", "author": "曾子榛", "section": "即時報導", "cover_image": {"src": "https://pgw.udn.com.tw/gw/photo.php?u=https://uc.udn.com.tw/photo/t3/2026/05/07/34927064.jpg&M=1&s=Y&x=0&y=0&sw=1280&sh=854&sl=W&fw=800&exp=3600&w=930", "alt": "世界衛生組織秘書長譚德塞7日於日內瓦舉行視訊記者會，針對郵輪漢他病毒群聚感染事件發表談話。法新社", "caption": "世界衛生組織秘書長譚德塞7日於日內瓦舉行視訊記者會，針對郵輪漢他病毒群聚感染事件發表談話。法新社"}, "body": [{"type": "text", "content": "BBC報導，英國衛生安全局發布最新消息，表示4月24日有七名英國籍旅客自爆發漢他病毒疫情的洪迪亞斯號下船，其中兩人已返回英國進行自主隔離，其餘人員尚未入境。已知有四人仍留在聖赫勒拿島，英方正與當地衛生官員保持聯繫，針對接觸者管理提供建議。"}, {"type": "text", "content": "該局說，目前仍在追蹤第七人行蹤。"}, {"type": "text", "content": "世衛組織7日在瑞士日內瓦舉行記者會，世衛流行病學家范科霍芙要求仍在洪迪亞斯號上所有人員「皆應配戴口罩」。她也補充，所有與疑似病例有接觸或負責照護的人員，皆應「穿戴等級更高的個人防護裝」。"}, {"type": "text", "content": "范科霍芙說，病例數可能增加，表示追蹤接觸者確實有效。她表示這次引發疫情的安地斯病毒株雖然會人與人，但只會透過密切接觸傳播。她同時說，漢他病毒不是新冠也不是流感，傳播途徑大不相同。"}, {"type": "text", "content": "她說：「我想強調，本次爆發在船上的病毒疫情，不是六年前的新冠病毒，更非另一場新冠疫情開端。」"}, {"type": "text", "content": "她表示，漢他病毒是透過「近距離親密接觸」感染，與新冠病毒不同，目前在船上採取的措施皆屬「預防性」，防止疫情進一步擴散。"}]}