{"article_id": "9520653", "title": "川普改行程 美媒：華府擬對伊朗新一輪軍事打擊", "date": "2026-05-23 09:36", "source": "中央社", "author": "華盛頓22日綜合外電報導", "section": "", "cover_image": {"src": "https://pgw.udn.com.tw/gw/photo.php?u=https://uc.udn.com.tw/photo/t3/2026/05/23/34974594.jpg&M=1&s=Y&x=0&y=0&sw=1280&sh=854&sl=W&fw=930&exp=3600&w=930", "alt": "美國總統川普。美聯社", "caption": "美國總統川普。美聯社"}, "body": [{"type": "text", "content": "美國媒體哥倫比亞廣播公司（CBS）和Axios今天報導，美國正考慮對伊朗發動新一輪軍事打擊。"}, {"type": "text", "content": "法新社提到，美國總統川普稍早表示，由於「與政府有關的情勢」以及他「對美國的熱愛」，他本週末不會前往參加兒子小唐納．川普（Donald Trump Jr.）的婚禮。"}, {"type": "text", "content": "川普說：「對我來說，在這個重要時期留在華盛頓特區的白宮很重要。」"}, {"type": "text", "content": "CBS和Axios報導均提到，川普尚未就新一輪打擊做出最終決定。"}, {"type": "text", "content": "據說相關談判仍在進行中，居中斡旋的巴基斯坦已派遣軍方首長前往伊朗德黑蘭（Tehran），試圖促成協議。"}, {"type": "text", "content": "法新社向白宮詢問相關報導，白宮未予置評。"}, {"type": "text", "content": "CBS報導說，白宮發言人凱利（Anna Kelly）告訴他們：「總統已明確表示，若伊朗未能達成協議將面臨後果。」"}, {"type": "text", "content": "白宮今天稍早宣布川普週末行程調整，表示他不會如原定計畫前往紐澤西州高爾夫度假村，而是留在華府。"}, {"type": "text", "content": "川普今天結束紐約州行程返回時，並未如往常般接受隨行記者提問。"}, {"type": "text", "content": "Axios引述兩名不具名消息人士說法報導，川普過去幾天對與伊朗的談判「日益感到挫折」。報導說，他本週的立場已從傾向外交轉為下令空襲。"}, {"type": "text", "content": "CBS也引述不具名消息人士報導，美國軍事與情報單位成員陸續取消週末假期計畫，為可能的軍事行動預做準備。"}]}