{"article_id": "9566510", "title": "船隻動起來了！受困波灣三個月的LNG船開往荷莫茲海峽 LNG價格大跌", "date": "2026-06-15 07:45", "source": "經濟日報", "author": "葉亭均", "section": "綜合外電", "cover_image": {"src": "https://pgw.udn.com.tw/gw/photo.php?u=https://uc.udn.com.tw/photo/t3/2026/06/15/35043846.jpg&M=1&s=Y&x=0&y=0&sw=1280&sh=720&sl=W&fw=930&exp=3600&w=930", "alt": "阿曼沿岸的荷莫茲海峽仍停泊許多船隻。路透", "caption": "阿曼沿岸的荷莫茲海峽仍停泊許多船隻。路透"}, "body": [{"type": "text", "content": "一艘液化天然氣（LNG）運輸船在受困於波斯灣超過三個月後，現在顯然正朝著荷莫茲海峽航行，值此之際，美國與伊朗表示雙方已達成終結戰爭的協議，美國總統川普隨後發文表示，海峽將於周五開放。"}, {"type": "text", "content": "根據彭博彙整的船舶追蹤資料顯示，名為Disha的LNG運輸船目前位於阿聯北方海域，正接近阿曼。該船長期租賃給一家印度國營天然氣進口商。"}, {"type": "text", "content": "資料顯示，Disha大約於3月1日在卡達拉斯拉凡天然氣出口設施裝載一批LNG貨物，但此後一直無法駛離波斯灣。"}, {"type": "text", "content": "然而，截至周一清晨，荷莫茲峽周邊的其他船舶活動仍相當有限。儘管美國宣布並獲伊朗證實已達成相關協議，但由於協議細節尚未公開，船東與能源交易商仍保持謹慎態度。"}, {"type": "text", "content": "從2月底美國與以色列對伊朗展開軍事打擊以來，荷莫茲海峽實際上一直處於封閉狀態。即使美伊達成的協議理論上能夠解除航道封鎖，並終結雙方互相實施的封鎖措施，但實際恢復正常通航仍將面臨不少挑戰，因為伊朗憑藉對荷莫茲海峽的控制權，仍握有相當大的戰略籌碼。"}, {"type": "text", "content": "受上述消息影響，歐洲天然氣價格在周一亞洲早盤一度下跌5.8%。若LNG船隻能恢復經由荷莫茲海峽運輸，將有助於緩解自3月以來推升歐洲與亞洲天然氣價格的供應緊張局面。"}, {"type": "text", "content": "油價也在開盤後大幅走低，布蘭特原油價格一度重挫超過4%，下探至每桶83.51美元；西德州原油期貨也挫跌4.4%，至每桶81.11美元。"}]}