{"article_id": "9603649", "title": "基輔遭俄軍大規模空襲 澤倫斯基盼美授權愛國者飛彈生產", "date": "2026-07-02 21:07", "source": "中央社", "author": "基輔2日綜合外電報導", "section": "", "cover_image": {"src": "https://pgw.udn.com.tw/gw/photo.php?u=https://uc.udn.com.tw/photo/t3/2026/07/02/35099375.jpg&M=1&s=Y&x=0&y=0&sw=1280&sh=853&sl=W&fw=930&exp=3600&w=930", "alt": "圖為美國愛國者飛彈系統。路透", "caption": "圖為美國愛國者飛彈系統。路透"}, "body": [{"type": "text", "content": "烏克蘭首都基輔夜間遭俄羅斯空襲造成至少17死，基輔市長克里契科稱這是俄國入侵烏克蘭後對基輔的最大規模攻擊。總統澤倫斯基表示，盼美國授權愛國者飛彈生產及其他合作形式。"}, {"type": "text", "content": "法新社報導，救難人員持續在一棟被摧毀的公寓大樓瓦礫中尋找生還者之際，克里契科（VitaliKlitschko）今天在社群媒體發文說：「訂明天7月3日為基輔的哀悼日，以悼念在首都遭遇敵軍最大規模攻擊中喪生的民眾。」"}, {"type": "text", "content": "烏克蘭總統澤倫斯基（Volodymyr Zelenskyy）今天稍晚表示，他已請求美國核發讓烏克蘭生產愛國者（Patriot）防空飛彈的許可證。"}, {"type": "text", "content": "澤倫斯基在社群媒體臉書（Facebook）發文說：「為烏克蘭提供防空物資是絕對且至關重要的優先事項…我們引頸期盼美國就授權愛國者飛彈製造及其他形式合作做出決定。」"}]}